{
  "uuid": "4e92bbc7-1e76-476f-9aea-61074c039fcf",
  "name": "ПакетОбменСБанками",
  "name2": {},
  "comment": "",
  "h1_0": "1",
  "h0": "3",
  "h5": [
    "1",
    "1",
    "9595ddd6-e72c-47ad-a156-672db811628c",
    "2",
    "8e9e7665-fa3a-4066-977c-d61996c36e5c",
    "0"
  ],
  "data": [
    [
      "1",
      [
        "40",
        "4daec07c-879e-4d07-9ec0-13c7228fa844",
        "d3fa7e6d-4d57-4a0d-8327-af9e97a17993",
        "59c48b01-7121-4a42-bfcc-44eecc262375",
        "e0905a1c-9006-4ae4-b407-17da84dfe2c8",
        "4bef563e-f2fb-4f8a-926b-2c82f02f6366",
        "1d1c91f4-5425-41d6-9169-08fada3bbf11",
        "d9af17bd-9840-4a16-8b08-ceb0d35c578d",
        "5e326737-aece-4892-9e20-77294048a40c",
        [
          "0",
          [
            "3",
            [
              "1",
              "0",
              "4e92bbc7-1e76-476f-9aea-61074c039fcf"
            ],
            "\"ПакетОбменСБанками\"",
            [
              "0"
            ],
            "\"\"",
            "1",
            "1",
            "9595ddd6-e72c-47ad-a156-672db811628c",
            "2",
            "8e9e7665-fa3a-4066-977c-d61996c36e5c",
            "0"
          ]
        ],
        "00000000-0000-0000-0000-000000000000",
        "1",
        "9",
        "0",
        "1",
        "1",
        "00000000-0000-0000-0000-000000000000",
        "00000000-0000-0000-0000-000000000000",
        "00000000-0000-0000-0000-000000000000",
        "0",
        "2",
        "0",
        [
          "0",
          "0"
        ],
        "1",
        [
          "0",
          "0"
        ],
        "0",
        "f7a8fc48-9e8e-494b-858d-4e3ebb7eeae1",
        "c9cf4c9c-cb37-4f56-bf20-360516c9f2c9",
        "0",
        [
          "1",
          [
            "0",
            "1",
            [
              "\"#\"",
              "60ea359f-3a6e-48bb-8e71-d2a457572918",
              [
                "-2"
              ]
            ]
          ]
        ],
        "1",
        "1",
        [
          "0"
        ],
        "1",
        "1",
        "00000000-0000-0000-0000-000000000000",
        "00000000-0000-0000-0000-000000000000",
        "00000000-0000-0000-0000-000000000000",
        [
          "0"
        ],
        [
          "0"
        ],
        [
          "0"
        ],
        [
          "0"
        ],
        [
          "0"
        ],
        "0",
        "1",
        [
          "0",
          [
            "0"
          ]
        ],
        "2",
        [
          "1",
          [
            "0",
            "0"
          ]
        ],
        [
          "1",
          "2",
          "0"
        ],
        "0",
        "0",
        "0",
        "0"
      ],
      "5",
      [
        "21c53e09-8950-4b5e-a6a0-1054f1bbc274",
        "0"
      ],
      [
        "3daea016-69b7-4ed4-9453-127911372fe6",
        "0"
      ],
      [
        "45e46cbc-3e24-4165-8b7b-cc98a6f80211",
        "1",
        [
          [
            "5",
            [
              "27",
              [
                "2",
                [
                  "3",
                  [
                    "1",
                    "0",
                    "02decddc-42f1-4f44-ba11-7fd3b4f68c03"
                  ],
                  "\"Организация\"",
                  [
                    "0"
                  ],
                  "\"\"",
                  "1",
                  "2",
                  "9595ddd6-e72c-47ad-a156-672db811628c",
                  "2",
                  "b1053250-abe6-11d4-9434-004095e12fc7",
                  "2",
                  "51166ba8-3d11-4778-90aa-2e26af20ab78",
                  "0"
                ],
                [
                  "\"Pattern\"",
                  [
                    "\"#\"",
                    "ccbccc52-1950-4c1f-b48e-5a0e86769dba"
                  ]
                ]
              ],
              "0",
              [
                "0"
              ],
              [
                "0"
              ],
              "0",
              "\"\"",
              "0",
              [
                "\"U\""
              ],
              [
                "\"U\""
              ],
              "0",
              "00000000-0000-0000-0000-000000000000",
              "2",
              "0",
              [
                "5006",
                "0"
              ],
              [
                "3",
                "0",
                "0"
              ],
              [
                "0",
                "0"
              ],
              "0",
              [
                "0"
              ],
              [
                "\"S\"",
                "\"\""
              ],
              "0",
              "0",
              "0"
            ],
            "0",
            "1",
            "1"
          ],
          "0"
        ]
      ],
      [
        "b544fc6a-2ba3-4885-8fb2-cb289fb6d65e",
        "0"
      ],
      [
        "fb880e93-47d7-4127-9357-a20e69c17545",
        "0"
      ]
    ]
  ]
}