{
  "uuid": "46bdda95-eb37-4f57-b835-2a07556e165d",
  "name": "ПачкаДокументовСЗВ_К",
  "name2": {},
  "comment": "",
  "h1_0": "1",
  "h0": "3",
  "h5": [
    "1",
    "1",
    "9595ddd6-e72c-47ad-a156-672db811628c",
    "2",
    "896985b3-c996-4f78-8c40-e725653b371a",
    "0"
  ],
  "data": [
    [
      "1",
      [
        "40",
        "80959e0c-5c1a-4954-a20d-f96d05a57b76",
        "ac7e6987-a23c-4b92-83e3-4a4a907743ad",
        "5685cddb-3a0c-44a5-ada4-e5312b0a8987",
        "5aae1dc2-b5f9-42e1-a9ff-d28d969378d7",
        "b7cb24fa-1dd9-41b4-978a-53be081b6861",
        "08d251f3-cd20-4598-a17e-559df0eb47e3",
        "8a0583c0-717a-40a3-8aeb-70047abb76a8",
        "fd06e18e-5533-4887-8cd5-42625b60639b",
        [
          "0",
          [
            "3",
            [
              "1",
              "0",
              "46bdda95-eb37-4f57-b835-2a07556e165d"
            ],
            "\"ПачкаДокументовСЗВ_К\"",
            [
              "0"
            ],
            "\"\"",
            "1",
            "1",
            "9595ddd6-e72c-47ad-a156-672db811628c",
            "2",
            "896985b3-c996-4f78-8c40-e725653b371a",
            "0"
          ]
        ],
        "00000000-0000-0000-0000-000000000000",
        "1",
        "9",
        "0",
        "1",
        "1",
        "00000000-0000-0000-0000-000000000000",
        "00000000-0000-0000-0000-000000000000",
        "00000000-0000-0000-0000-000000000000",
        "0",
        "2",
        "0",
        [
          "0",
          "0"
        ],
        "1",
        [
          "0",
          "0"
        ],
        "0",
        "af75244b-e464-487b-8ef4-5b32655ad8b0",
        "dba5b2f5-a8de-4e31-9be8-acd88a34b2cb",
        "0",
        [
          "1",
          [
            "0",
            "1",
            [
              "\"#\"",
              "60ea359f-3a6e-48bb-8e71-d2a457572918",
              [
                "-2"
              ]
            ]
          ]
        ],
        "1",
        "1",
        [
          "0"
        ],
        "1",
        "1",
        "00000000-0000-0000-0000-000000000000",
        "00000000-0000-0000-0000-000000000000",
        "00000000-0000-0000-0000-000000000000",
        [
          "0"
        ],
        [
          "0"
        ],
        [
          "0"
        ],
        [
          "0"
        ],
        [
          "0"
        ],
        "0",
        "1",
        [
          "0",
          [
            "0"
          ]
        ],
        "2",
        [
          "1",
          [
            "0",
            "0"
          ]
        ],
        [
          "1",
          "2",
          "0"
        ],
        "0",
        "0",
        "0",
        "0"
      ],
      "5",
      [
        "21c53e09-8950-4b5e-a6a0-1054f1bbc274",
        "0"
      ],
      [
        "3daea016-69b7-4ed4-9453-127911372fe6",
        "0"
      ],
      [
        "45e46cbc-3e24-4165-8b7b-cc98a6f80211",
        "1",
        [
          [
            "5",
            [
              "27",
              [
                "2",
                [
                  "3",
                  [
                    "1",
                    "0",
                    "fd9e99fe-0937-4408-bace-acab71111577"
                  ],
                  "\"Организация\"",
                  [
                    "0"
                  ],
                  "\"\"",
                  "1",
                  "2",
                  "9595ddd6-e72c-47ad-a156-672db811628c",
                  "2",
                  "b1053250-abe6-11d4-9434-004095e12fc7",
                  "2",
                  "83d438b9-bd86-47f8-9f0d-b7c51f95f709",
                  "0"
                ],
                [
                  "\"Pattern\"",
                  [
                    "\"#\"",
                    "008662c0-50f4-4dab-8822-87f3cbc3a155"
                  ]
                ]
              ],
              "0",
              [
                "0"
              ],
              [
                "0"
              ],
              "0",
              "\"\"",
              "0",
              [
                "\"U\""
              ],
              [
                "\"U\""
              ],
              "0",
              "00000000-0000-0000-0000-000000000000",
              "2",
              "0",
              [
                "5006",
                "0"
              ],
              [
                "3",
                "0",
                "0"
              ],
              [
                "0",
                "0"
              ],
              "0",
              [
                "0"
              ],
              [
                "\"S\"",
                "\"\""
              ],
              "0",
              "0",
              "0"
            ],
            "0",
            "1",
            "1"
          ],
          "0"
        ]
      ],
      [
        "b544fc6a-2ba3-4885-8fb2-cb289fb6d65e",
        "0"
      ],
      [
        "fb880e93-47d7-4127-9357-a20e69c17545",
        "0"
      ]
    ]
  ]
}